JingduYitaiFangYuanma/README.md
JingduYitaiFangYuanma/__init__.py
JingduYitaiFangYuanma/__main__.py
JingduYitaiFangYuanma/file.epub
JingduYitaiFangYuanma/index.html
JingduYitaiFangYuanma/css/__init__.py
JingduYitaiFangYuanma/css/annotations.css
JingduYitaiFangYuanma/css/main.css
JingduYitaiFangYuanma/css/normalize.css
JingduYitaiFangYuanma/css/popup.css
JingduYitaiFangYuanma/font/__init__.py
JingduYitaiFangYuanma/font/fontello.eot
JingduYitaiFangYuanma/font/fontello.svg
JingduYitaiFangYuanma/font/fontello.ttf
JingduYitaiFangYuanma/font/fontello.woff
JingduYitaiFangYuanma/img/__init__.py
JingduYitaiFangYuanma/img/annotator-glyph-sprite.png
JingduYitaiFangYuanma/img/annotator-icon-sprite.png
JingduYitaiFangYuanma/img/apple-touch-icon.png
JingduYitaiFangYuanma/img/cancelfullscreen.png
JingduYitaiFangYuanma/img/close.png
JingduYitaiFangYuanma/img/fullscreen.png
JingduYitaiFangYuanma/img/loader.gif
JingduYitaiFangYuanma/img/menu-icon.png
JingduYitaiFangYuanma/img/save.png
JingduYitaiFangYuanma/img/saved.png
JingduYitaiFangYuanma/img/settings-s.png
JingduYitaiFangYuanma/img/settings.png
JingduYitaiFangYuanma/img/star.png
JingduYitaiFangYuanma/js/__init__.py
JingduYitaiFangYuanma/js/epub.js
JingduYitaiFangYuanma/js/epub.min.js
JingduYitaiFangYuanma/js/epub.min.map
JingduYitaiFangYuanma/js/hooks.min.js
JingduYitaiFangYuanma/js/hooks.min.map
JingduYitaiFangYuanma/js/reader.js
JingduYitaiFangYuanma/js/reader.js.map
JingduYitaiFangYuanma/js/reader.min.js
JingduYitaiFangYuanma/js/reader.min.map
JingduYitaiFangYuanma/js/hooks/__init__.py
JingduYitaiFangYuanma/js/hooks/extensions/__init__.py
JingduYitaiFangYuanma/js/hooks/extensions/highlight.js
JingduYitaiFangYuanma/js/libs/__init__.py
JingduYitaiFangYuanma/js/libs/jquery.min.js
JingduYitaiFangYuanma/js/libs/localforage.min.js
JingduYitaiFangYuanma/js/libs/screenfull.js
JingduYitaiFangYuanma/js/libs/screenfull.min.js
JingduYitaiFangYuanma/js/libs/zip.min.js
JingduYitaiFangYuanma/js/plugins/__init__.py
jingdu_yitai_fang_yuanma-2024.3.4.0.dist-info/METADATA
jingdu_yitai_fang_yuanma-2024.3.4.0.dist-info/WHEEL
jingdu_yitai_fang_yuanma-2024.3.4.0.dist-info/entry_points.txt
jingdu_yitai_fang_yuanma-2024.3.4.0.dist-info/top_level.txt
jingdu_yitai_fang_yuanma-2024.3.4.0.dist-info/RECORD
